nsdev/__init__.py
nsdev/addUser.py
nsdev/argument.py
nsdev/bing.py
nsdev/button.py
nsdev/colorize.py
nsdev/database.py
nsdev/encrypt.py
nsdev/gemini.py
nsdev/gradient.py
nsdev/huggingface.py
nsdev/listen.py
nsdev/logger.py
nsdev/payment.py
nsdev/storekey.py
nsdev/ymlreder.py
norsodikin-1.0.7.1.dist-info/METADATA
norsodikin-1.0.7.1.dist-info/WHEEL
norsodikin-1.0.7.1.dist-info/top_level.txt
norsodikin-1.0.7.1.dist-info/RECORD
