Metadata-Version: 2.4
Name: norsodikin
Version: 1.0.7.1
Summary: Library of special mission and encrypted code
Author-email: NorSodikin <admin@NorSodikin.com>
License: MIT
Project-URL: Homepage, https://github.com/SenpaiSeeker/norsodikin
Classifier: Programming Language :: Python :: 3
Classifier: Programming Language :: Python :: 3.9
Classifier: Programming Language :: Python :: 3.10
Classifier: Programming Language :: Python :: 3.11
Classifier: Programming Language :: Python :: 3.12
Classifier: License :: OSI Approved :: MIT License
Classifier: Operating System :: OS Independent
Requires-Python: <3.13,>=3.9
Requires-Dist: aiohttp
Requires-Dist: pyfiglet
Requires-Dist: pyyaml
Requires-Dist: httpx
Requires-Dist: requests
Requires-Dist: fake-useragent
Requires-Dist: faker
Provides-Extra: pyrogram
Requires-Dist: pyrotgfork[fast]; extra == "pyrogram"
Requires-Dist: pymongo; extra == "pyrogram"
